alluvium/__init__.py
alluvium/config.py
alluvium/main.py
alluvium/overlay.py
alluvium-0.1.1.dist-info/LICENSE
alluvium-0.1.1.dist-info/METADATA
alluvium-0.1.1.dist-info/WHEEL
alluvium-0.1.1.dist-info/entry_points.txt
alluvium-0.1.1.dist-info/top_level.txt
alluvium-0.1.1.dist-info/RECORD
