Metadata-Version: 2.1
Name: alluvium
Version: 0.1.1
Summary: Interactive bindings visualizer for i3
Home-page: https://github.com/cqql/alluvium
Author: Marten Lienen
Author-email: marten.lienen@gmail.com
License: UNKNOWN
Platform: UNKNOWN
Requires-Python: >=3.6
Requires-Dist: i3ipc
Requires-Dist: PyGObject
